trava/__init__.py
trava/evaluator.py
trava/fit_predictor.py
trava/logger.py
trava/metric.py
trava/model_info.py
trava/model_results.py
trava/model_serializer.py
trava/raw_dataset.py
trava/results_handler.py
trava/scorer.py
trava/scorers_provider.py
trava/tracker.py
trava/trava_base.py
trava/trava_model.py
trava/trava_sv.py
trava/trava_tracker.py
trava/ext/__init__.py
trava/ext/boosting_eval/__init__.py
trava/ext/boosting_eval/boosting_logic.py
trava/ext/boosting_eval/catboost_logic.py
trava/ext/boosting_eval/eval_steps.py
trava/ext/boosting_eval/lightgbm_logic.py
trava/ext/boosting_eval/xgboost_logic.py
trava/ext/cv/__init__.py
trava/ext/cv/base.py
trava/ext/cv/cv_fit_predictor.py
trava/ext/cv/sk.py
trava/ext/grouped/__init__.py
trava/ext/grouped/group_analysis_fit_predictor.py
trava/ext/grouped/group_scorer.py
trava/ext/grouped/group_steps.py
trava/ext/model_serializer/__init__.py
trava/ext/model_serializer/pickle.py
trava/ext/model_serializer/xgboost.py
trava/ext/plots/__init__.py
trava/ext/plots/confustion_matrix.py
trava/ext/plots/roc.py
trava/ext/results_handlers/__init__.py
trava/ext/results_handlers/logger.py
trava/ext/results_handlers/metrics_dict.py
trava/ext/results_handlers/pandas_df.py
trava/ext/results_handlers/plotter.py
trava/ext/results_handlers/scorer_plotter.py
trava/ext/scorers/__init__.py
trava/ext/scorers/model_scorers.py
trava/ext/sklearn/__init__.py
trava/ext/sklearn/preproc_step.py
trava/ext/sklearn/scorers.py
trava/ext/split_logic/__init__.py
trava/ext/split_logic/basic.py
trava/ext/split_logic/time.py
trava/ext/split_logic/within_group.py
trava/ext/tracker/__init__.py
trava/ext/tracker/mlflow.py
trava/split/__init__.py
trava/split/config.py
trava/split/logic.py
trava/split/result.py
trava/split/splitter.py
trava/utils/__init__.py
trava/utils/model_params_filter.py
trava/utils/tmp.py
trava-0.2.12.dist-info/METADATA
trava-0.2.12.dist-info/WHEEL
trava-0.2.12.dist-info/top_level.txt
trava-0.2.12.dist-info/RECORD
