Metadata-Version: 2.1
Name: trava
Version: 0.2.12
Summary: Framework that helps to train models, compare them and track parameters&metrics along the way.
Home-page: https://github.com/ityutin/trava
Author: Ilya Tyutin
Author-email: emmarrgghh@gmail.com
License: MIT
Platform: UNKNOWN
Classifier: License :: OSI Approved :: MIT License
Classifier: Programming Language :: Python :: 3
Classifier: Programming Language :: Python :: 3.7
Requires-Dist: pandas
Requires-Dist: numpy
